CHANGELOG.md
README.md
chapter_sync/__init__.py
chapter_sync/__main__.py
chapter_sync/chapter.py
chapter_sync/cli/__init__.py
chapter_sync/cli/base.py
chapter_sync/cli/chapter.py
chapter_sync/cli/db.py
chapter_sync/cli/series.py
chapter_sync/cli/subscriber.py
chapter_sync/console.py
chapter_sync/cover.py
chapter_sync/db.py
chapter_sync/email.py
chapter_sync/epub.py
chapter_sync/handlers/__init__.py
chapter_sync/handlers/base.py
chapter_sync/handlers/custom.py
chapter_sync/handlers/royal_road.py
chapter_sync/migrations/__init__.py
chapter_sync/migrations/alembic.ini
chapter_sync/migrations/env.py
chapter_sync/migrations/script.py.mako
chapter_sync/migrations/versions/63139caea00e_initial_tables.py
chapter_sync/migrations/versions/__init__.py
chapter_sync/py.typed
chapter_sync/request.py
chapter_sync/schema.py
chapter_sync/series.py
chapter_sync/subscriber.py
chapter_sync/sync.py
chapter_sync/templates/__init__.py
chapter_sync/templates/base.css
chapter_sync/web/__init__.py
chapter_sync/web/chapter.py
chapter_sync/web/dependencies.py
chapter_sync/web/main.py
chapter_sync/web/routes.py
chapter_sync/web/series.py
chapter_sync/web/static/__init__.py
chapter_sync/web/static/app.css
chapter_sync/web/static/favicon.ico
chapter_sync/web/static/icon.svg
chapter_sync/web/static/styles.css
chapter_sync/web/subscriber.py
chapter_sync/web/templates/__init__.py
chapter_sync/web/templates/base.html
chapter_sync/web/templates/chapter.html
chapter_sync/web/templates/header.html
chapter_sync/web/templates/index.html
chapter_sync/web/templates/macros.html
chapter_sync/web/templates/series.html
chapter_sync/web/templates/subscriber.html
chapter_sync/web/templates/subscribers.html
chapter_sync-0.3.7.dist-info/LICENSE
chapter_sync-0.3.7.dist-info/METADATA
chapter_sync-0.3.7.dist-info/WHEEL
chapter_sync-0.3.7.dist-info/entry_points.txt
chapter_sync-0.3.7.dist-info/RECORD
