Metadata-Version: 2.1
Name: chapter-sync
Version: 0.3.7
Summary: 
Home-page: https://github.com/dancardin/sqlalchemy-declarative-extensions
License: Apache-2.0
Keywords: chapter,sync,epub,ebook,leech
Author: Dan Cardin
Author-email: ddcardin@gmail.com
Requires-Python: >=3.10,<4.0
Classifier: License :: OSI Approved :: Apache Software License
Classifier: Programming Language :: Python :: 3
Classifier: Programming Language :: Python :: 3.10
Classifier: Programming Language :: Python :: 3.11
Classifier: Programming Language :: Python :: 3.12
Requires-Dist: Pillow (>=10.0.0,<11.0.0)
Requires-Dist: alembic (>=1.9.0)
Requires-Dist: beautifulsoup4 (>=4.9.3,<5.0.0)
Requires-Dist: cappa (>=0.18.1)
Requires-Dist: dataclass-settings (>=0.2.3,<0.3.0)
Requires-Dist: fastapi
Requires-Dist: html5lib (>=1.1,<2.0)
Requires-Dist: jinja2
Requires-Dist: pendulum (>=2)
Requires-Dist: pydantic (>=2)
Requires-Dist: python-dotenv
Requires-Dist: python-multipart (>=0.0.9,<0.0.10)
Requires-Dist: requests
Requires-Dist: rich
Requires-Dist: sqlalchemy (>=2.0)
Requires-Dist: uvicorn
Requires-Dist: xmltodict
Project-URL: Repository, https://github.com/dancardin/sqlalchemy-declarative-extensions
